{"version":1,"resource":"file:///home/I40S/Projects_school/large_modal/Underground-parking-system-FRONTEND/combined.html","entries":[{"id":"VqPh.html","source":"undoRedo.source","timestamp":1708936400607},{"id":"rsQ6.html","timestamp":1708936519651},{"id":"Jow6.html","source":"undoRedo.source","timestamp":1708936541518},{"id":"dbFc.html","timestamp":1708936665091},{"id":"gMzZ.html","source":"undoRedo.source","timestamp":1708936766648},{"id":"WmyL.html","timestamp":1708936777802},{"id":"HVoI.html","source":"undoRedo.source","timestamp":1708936811008},{"id":"w9cV.html","timestamp":1708937282588},{"id":"8j4g.html","timestamp":1708937311935},{"id":"EBiT.html","source":"undoRedo.source","timestamp":1708937352482},{"id":"UZXB.html","timestamp":1708937564057},{"id":"YRDA.html","timestamp":1708937590657},{"id":"TBMG.html","timestamp":1708937632074},{"id":"R1qt.html","source":"undoRedo.source","timestamp":1708937642630},{"id":"78Dk.html","timestamp":1708937660000},{"id":"Tg1X.html","source":"undoRedo.source","timestamp":1708937662984},{"id":"aBoQ.html","timestamp":1708937680150},{"id":"qTni.html","source":"undoRedo.source","timestamp":1708937786061},{"id":"8pO1.html","timestamp":1708937797801},{"id":"epbB.html","timestamp":1708937811818},{"id":"2Np0.html","timestamp":1708937825465},{"id":"fsTA.html","timestamp":1708937844928},{"id":"0LAU.html","source":"undoRedo.source","timestamp":1708937884705},{"id":"sZ7i.html","timestamp":1708937886545},{"id":"uGRn.html","timestamp":1708938051139},{"id":"OY0x.html","timestamp":1708938081492},{"id":"DmJ7.html","timestamp":1708938095662},{"id":"P7gU.html","timestamp":1708938396313},{"id":"zcw3.html","source":"undoRedo.source","timestamp":1708938408817},{"id":"vPbf.html","timestamp":1708938460460},{"id":"CWYX.html","timestamp":1708938479987},{"id":"4g78.html","timestamp":1708938498064},{"id":"BC9n.html","timestamp":1708938581271},{"id":"eVhX.html","timestamp":1709022014024},{"id":"1FBj.html","timestamp":1709022315785},{"id":"XDdt.html","timestamp":1709022328315},{"id":"NIoT.html","source":"undoRedo.source","timestamp":1709022331369},{"id":"i2Ba.html","timestamp":1709022394996},{"id":"qTYz.html","source":"undoRedo.source","timestamp":1709022416899},{"id":"V4r1.html","timestamp":1709023083248},{"id":"9h3o.html","source":"undoRedo.source","timestamp":1709023087894},{"id":"bKRZ.html","timestamp":1709023106071},{"id":"ank5.html","source":"undoRedo.source","timestamp":1709023389998},{"id":"NIhx.html","timestamp":1709023398565},{"id":"EhFf.html","timestamp":1709023524856},{"id":"aCvA.html","timestamp":1709023565916},{"id":"vpsU.html","timestamp":1709023578886},{"id":"CrQo.html","timestamp":1709023594243},{"id":"RhXW.html","source":"undoRedo.source","timestamp":1709023782231},{"id":"b3H7.html","timestamp":1709023877015}]}