{"version":1,"resource":"file:///home/I40S/.config/eww/scss/bar.scss","entries":[{"id":"eUup.scss","timestamp":1711455221227},{"id":"IHzt.scss","source":"undoRedo.source","timestamp":1711455226033},{"id":"Ckyo.scss","timestamp":1711455549777},{"id":"dzxs.scss","source":"undoRedo.source","timestamp":1711455553717},{"id":"g7B2.scss","timestamp":1711455668727},{"id":"Ums7.scss","source":"undoRedo.source","timestamp":1711455671147},{"id":"O5L5.scss","timestamp":1711455701553},{"id":"6AQy.scss","source":"undoRedo.source","timestamp":1711455711673},{"id":"06pu.scss","timestamp":1711455729540},{"id":"uDWA.scss","timestamp":1711487244639},{"id":"V8h9.scss","source":"undoRedo.source","timestamp":1711487250526},{"id":"9Vpz.scss","timestamp":1711487279659},{"id":"IxZy.scss","source":"undoRedo.source","timestamp":1711487443415},{"id":"eIo4.scss","timestamp":1711487444568},{"id":"uWly.scss","timestamp":1711487646897},{"id":"s569.scss","source":"undoRedo.source","timestamp":1711487651741},{"id":"gAqK.scss","timestamp":1711535114440},{"id":"21wm.scss","timestamp":1712208355840},{"id":"gqB3.scss","source":"undoRedo.source","timestamp":1712208370673},{"id":"xixl.scss","timestamp":1712413173441},{"id":"3UqC.scss","source":"undoRedo.source","timestamp":1712413176998},{"id":"YDuL.scss","timestamp":1712413201714},{"id":"WqLD.scss","timestamp":1712413462453},{"id":"rkfh.scss","source":"undoRedo.source","timestamp":1712413466343},{"id":"Vx1y.scss","timestamp":1712413480247},{"id":"Cvmn.scss","timestamp":1712413537621},{"id":"bY30.scss","source":"undoRedo.source","timestamp":1712413562528},{"id":"2uLo.scss","timestamp":1712413566424},{"id":"CcF2.scss","source":"undoRedo.source","timestamp":1712413569221},{"id":"6jMH.scss","timestamp":1712486914648},{"id":"el6I.scss","timestamp":1712568729283},{"id":"Sj87.scss","timestamp":1712569136313},{"id":"0yRF.scss","timestamp":1712569148287},{"id":"t36y.scss","timestamp":1712569366297},{"id":"DH2r.scss","timestamp":1712569442183},{"id":"5iN3.scss","source":"undoRedo.source","timestamp":1712569443917},{"id":"NOFU.scss","timestamp":1712569447053},{"id":"FgnB.scss","timestamp":1712813266557},{"id":"4KWm.scss","source":"undoRedo.source","timestamp":1712813272387},{"id":"duGq.scss","timestamp":1713202445993},{"id":"32qM.scss","source":"undoRedo.source","timestamp":1713202450843},{"id":"TYzI.scss","timestamp":1713207699828},{"id":"7Hac.scss","timestamp":1713208500690},{"id":"Z6Af.scss","source":"undoRedo.source","timestamp":1713208507316},{"id":"6DOM.scss","timestamp":1713208511506},{"id":"rdiE.scss","source":"undoRedo.source","timestamp":1713208528759}]}