{"version":1,"resource":"file:///home/I40S/.config/eww/modules/control_center.yuck","entries":[{"id":"RnxU.yuck","timestamp":1712658780289},{"id":"IufV.yuck","timestamp":1712658822085},{"id":"Hlxm.yuck","timestamp":1712658838849},{"id":"1QjQ.yuck","source":"undoRedo.source","timestamp":1712658849535},{"id":"hBdx.yuck","timestamp":1712658864282},{"id":"tqHF.yuck","timestamp":1712733823960},{"id":"opWG.yuck","source":"undoRedo.source","timestamp":1712733829100},{"id":"ArsW.yuck","timestamp":1712813073690},{"id":"mHT5.yuck","timestamp":1712813095823},{"id":"etVg.yuck","timestamp":1712813232857},{"id":"lHXV.yuck","timestamp":1713177031405},{"id":"3Uqi.yuck","timestamp":1713177059606}]}